{
  "_class": "group",
  "do_objectID": "F311B0F9-35BA-4469-BD53-EB8536E01188",
  "exportOptions": {
    "_class": "exportOptions",
    "exportFormats": [
    ],
    "includedLayerIds": [
    ],
    "layerOptions": 0,
    "shouldTrim": false
  },
  "frame": {
    "_class": "rect",
    "constrainProportions": false,
    "height": 64,
    "width": 255,
    "x": 0,
    "y": 96
  },
  "hasClickThrough": false,
  "isFlippedHorizontal": false,
  "isFlippedVertical": false,
  "isLocked": false,
  "isVisible": true,
  "layerListExpandedType": 0,
  "layers": [
    {
      "class": "shapeGroup",
      "id": "0C41D10C-81CA-4CD2-B19F-6C35A5034A45"
    },
    {
      "class": "group",
      "id": "4270174F-A950-43F8-BCA5-5213B7B29257"
    }
  ],
  "name": "Group 6",
  "nameIsFixed": false,
  "originalObjectID": "F311B0F9-35BA-4469-BD53-EB8536E01188",
  "resizingConstraint": 63,
  "resizingType": 0,
  "rotation": 0,
  "shouldBreakMaskChain": false,
  "style": {
    "_class": "style",
    "endDecorationType": 0,
    "miterLimit": 10,
    "startDecorationType": 0
  }
}