{
  "_class": "sharedStyle",
  "do_objectID": "AF5CEF13-4BA4-4388-90B3-125D577FD8AC",
  "name": "Image",
  "value": {
    "_class": "style",
    "endDecorationType": 0,
    "fills": [
      {
        "_class": "fill",
        "color": {
          "_class": "color",
          "alpha": 1,
          "blue": 0.9529411764705882,
          "green": 0.9490196078431372,
          "red": 0.9490196078431372
        },
        "fillType": 4,
        "image": {
          "_class": "MSJSONFileReference",
          "_ref": "images/b4e44abd77250d45f1a37bb989f98665435f3ad5",
          "_ref_class": "MSImageData"
        },
        "isEnabled": true,
        "noiseIndex": 0,
        "noiseIntensity": 0,
        "patternFillType": 1,
        "patternTileScale": 1
      }
    ],
    "miterLimit": 10,
    "sharedObjectID": "AF5CEF13-4BA4-4388-90B3-125D577FD8AC",
    "startDecorationType": 0
  }
}