{
  "_class": "shapeGroup",
  "clippingMaskMode": 0,
  "do_objectID": "29056258-D8B8-4B1D-8D61-9DB29ECD6FAE",
  "exportOptions": {
    "_class": "exportOptions",
    "exportFormats": [
    ],
    "includedLayerIds": [
    ],
    "layerOptions": 0,
    "shouldTrim": false
  },
  "frame": {
    "_class": "rect",
    "constrainProportions": false,
    "height": 28,
    "width": 104,
    "x": 2.842170943040402e-14,
    "y": 0
  },
  "hasClickThrough": false,
  "hasClippingMask": true,
  "isFlippedHorizontal": false,
  "isFlippedVertical": false,
  "isLocked": false,
  "isVisible": true,
  "layerListExpandedType": 1,
  "layers": [
    {
      "class": "rectangle",
      "id": "F24EA31C-C859-40D2-B0EC-381C384BCE37"
    }
  ],
  "name": "Mask",
  "nameIsFixed": false,
  "originalObjectID": "29056258-D8B8-4B1D-8D61-9DB29ECD6FAE",
  "resizingConstraint": 18,
  "resizingType": 2,
  "rotation": 0,
  "shouldBreakMaskChain": false,
  "style": {
    "_class": "style",
    "blur": {
      "_class": "blur",
      "center": "{0.5, 0.5}",
      "isEnabled": true,
      "motionAngle": 0,
      "radius": 1,
      "type": 3
    },
    "endDecorationType": 0,
    "miterLimit": 10,
    "shadows": [
      {
        "_class": "shadow",
        "blurRadius": 8,
        "color": {
          "_class": "color",
          "alpha": 0.15,
          "blue": 0.4509803921568628,
          "green": 0.380392156862745,
          "red": 0.3215686274509804
        },
        "contextSettings": {
          "_class": "graphicsContextSettings",
          "blendMode": 0,
          "opacity": 1
        },
        "isEnabled": true,
        "offsetX": 0,
        "offsetY": 4,
        "spread": 0
      }
    ],
    "startDecorationType": 0
  },
  "userInfo": {
    "com.animaapp.stc-sketch-plugin": {
      "kModelPropertiesKey": {
      }
    }
  },
  "windingRule": 1
}