{
  "_class": "shapePath",
  "booleanOperation": -1,
  "do_objectID": "07F41D27-4788-4B2A-895C-357CE6D2B2C6",
  "edited": true,
  "exportOptions": {
    "_class": "exportOptions",
    "exportFormats": [
    ],
    "includedLayerIds": [
    ],
    "layerOptions": 0,
    "shouldTrim": false
  },
  "frame": {
    "_class": "rect",
    "constrainProportions": false,
    "height": 19.706,
    "width": 19.707,
    "x": 0,
    "y": 0
  },
  "isFlippedHorizontal": false,
  "isFlippedVertical": false,
  "isLocked": false,
  "isVisible": true,
  "layerListExpandedType": 0,
  "name": "Path",
  "nameIsFixed": false,
  "path": {
    "_class": "path",
    "isClosed": true,
    "pointRadiusBehaviour": 0,
    "points": [
      {
        "_class": "curvePoint",
        "cornerRadius": 0,
        "curveFrom": "{1, 0.92829595047193747}",
        "curveMode": 1,
        "curveTo": "{1, 0.92829595047193747}",
        "hasCurveFrom": false,
        "hasCurveTo": false,
        "point": "{1, 0.92829595047193747}"
      },
      {
        "_class": "curvePoint",
        "cornerRadius": 0,
        "curveFrom": "{0.7816004465418378, 0.58378158936364555}",
        "curveMode": 4,
        "curveTo": "{0.72634089409854363, 0.65462295747488075}",
        "hasCurveFrom": true,
        "hasCurveTo": false,
        "point": "{0.72634089409854363, 0.65462295747488075}"
      },
      {
        "_class": "curvePoint",
        "cornerRadius": 0,
        "curveFrom": "{0.8118942507738367, 0.2975235968740485}",
        "curveMode": 3,
        "curveTo": "{0.8118942507738367, 0.49725971785243073}",
        "hasCurveFrom": true,
        "hasCurveTo": true,
        "point": "{0.8118942507738367, 0.40596772556581751}"
      },
      {
        "_class": "curvePoint",
        "cornerRadius": 0,
        "curveFrom": "{0.61632922311868876, 0.042220643458845013}",
        "curveMode": 2,
        "curveTo": "{0.76962500634292386, 0.19557495179133261}",
        "hasCurveFrom": true,
        "hasCurveTo": true,
        "point": "{0.69295174303546958, 0.11894854359078455}"
      },
      {
        "_class": "curvePoint",
        "cornerRadius": 0,
        "curveFrom": "{0.29750849951793773, 0}",
        "curveMode": 2,
        "curveTo": "{0.51438575125589892, 0}",
        "hasCurveFrom": true,
        "hasCurveTo": true,
        "point": "{0.40594712538691835, 0}"
      },
      {
        "_class": "curvePoint",
        "cornerRadius": 0,
        "curveFrom": "{0.042269244430912879, 0.19557495179133261}",
        "curveMode": 2,
        "curveTo": "{0.19556502765514791, 0.042220643458845013}",
        "hasCurveFrom": true,
        "hasCurveTo": true,
        "point": "{0.11894250773836709, 0.11894854359078455}"
      },
      {
        "_class": "curvePoint",
        "cornerRadius": 0,
        "curveFrom": "{0, 0.51441185425758651}",
        "curveMode": 2,
        "curveTo": "{0, 0.29752359687404856}",
        "hasCurveFrom": true,
        "hasCurveTo": true,
        "point": "{0, 0.40596772556581751}"
      },
      {
        "_class": "curvePoint",
        "cornerRadius": 0,
        "curveFrom": "{0.19556502765514791, 0.76971480767278999}",
        "curveMode": 2,
        "curveTo": "{0.042269244430912879, 0.61636049934030246}",
        "hasCurveFrom": true,
        "hasCurveTo": true,
        "point": "{0.11894250773836704, 0.69298690754085046}"
      },
      {
        "_class": "curvePoint",
        "cornerRadius": 0,
        "curveFrom": "{0.49723448520830155, 0.81193545113163501}",
        "curveMode": 3,
        "curveTo": "{0.29750849951793779, 0.81193545113163501}",
        "hasCurveFrom": true,
        "hasCurveTo": true,
        "point": "{0.40594712538691835, 0.81193545113163501}"
      },
      {
        "_class": "curvePoint",
        "cornerRadius": 0,
        "curveFrom": "{0.65458973968640588, 0.72637775296863905}",
        "curveMode": 4,
        "curveTo": "{0.58375196630638859, 0.78169085557698159}",
        "hasCurveFrom": false,
        "hasCurveTo": true,
        "point": "{0.65458973968640588, 0.72637775296863905}"
      },
      {
        "_class": "curvePoint",
        "cornerRadius": 0,
        "curveFrom": "{0.92824884558786214, 1}",
        "curveMode": 1,
        "curveTo": "{0.92824884558786214, 1}",
        "hasCurveFrom": false,
        "hasCurveTo": false,
        "point": "{0.92824884558786214, 1}"
      }
    ]
  },
  "resizingConstraint": 63,
  "resizingType": 0,
  "rotation": 0,
  "shouldBreakMaskChain": false
}