{
  "_class": "shapeGroup",
  "clippingMaskMode": 0,
  "do_objectID": "FA300617-EB38-4448-BBEF-CD9CD9E47F70",
  "exportOptions": {
    "_class": "exportOptions",
    "exportFormats": [
    ],
    "includedLayerIds": [
    ],
    "layerOptions": 0,
    "shouldTrim": false
  },
  "frame": {
    "_class": "rect",
    "constrainProportions": true,
    "height": 12,
    "width": 12,
    "x": 2.485281374237275,
    "y": 2.485281374238639
  },
  "hasClickThrough": false,
  "hasClippingMask": false,
  "isFlippedHorizontal": false,
  "isFlippedVertical": false,
  "isLocked": false,
  "isVisible": true,
  "layerListExpandedType": 0,
  "layers": [
    {
      "class": "rectangle",
      "id": "A31AF7B3-67B2-456F-B30E-0C4D991BF529"
    }
  ],
  "name": "Rectangle 166",
  "nameIsFixed": false,
  "originalObjectID": "FA300617-EB38-4448-BBEF-CD9CD9E47F70",
  "resizingConstraint": 63,
  "resizingType": 0,
  "rotation": 135,
  "shouldBreakMaskChain": false,
  "style": {
    "_class": "style",
    "borders": [
      {
        "_class": "border",
        "color": {
          "_class": "color",
          "alpha": 1,
          "blue": 0.592,
          "green": 0.592,
          "red": 0.592
        },
        "fillType": 0,
        "isEnabled": false,
        "position": 1,
        "thickness": 1
      }
    ],
    "endDecorationType": 0,
    "fills": [
      {
        "_class": "fill",
        "color": {
          "_class": "color",
          "alpha": 1,
          "blue": 0.337266156462585,
          "green": 0.337266156462585,
          "red": 0.337266156462585
        },
        "fillType": 0,
        "isEnabled": true,
        "noiseIndex": 0,
        "noiseIntensity": 0,
        "patternFillType": 0,
        "patternTileScale": 1
      }
    ],
    "miterLimit": 10,
    "startDecorationType": 0
  },
  "windingRule": 1
}