{
  "_class": "shapePath",
  "booleanOperation": -1,
  "do_objectID": "4FBEA504-2B0A-4CCC-86EF-E56622460183",
  "edited": true,
  "exportOptions": {
    "_class": "exportOptions",
    "exportFormats": [
    ],
    "includedLayerIds": [
    ],
    "layerOptions": 0,
    "shouldTrim": false
  },
  "frame": {
    "_class": "rect",
    "constrainProportions": false,
    "height": 1.353391304347824,
    "width": 1.389684964581844,
    "x": 0.9539007937215025,
    "y": 0.7419130434782621
  },
  "isFlippedHorizontal": false,
  "isFlippedVertical": false,
  "isLocked": false,
  "isVisible": true,
  "layerListExpandedType": 0,
  "name": "Path",
  "nameIsFixed": false,
  "path": {
    "_class": "path",
    "isClosed": true,
    "pointRadiusBehaviour": 1,
    "points": [
      {
        "_class": "curvePoint",
        "cornerRadius": 0,
        "curveFrom": "{0.94413107391568452, 0.80185042405551277}",
        "curveMode": 4,
        "curveTo": "{1.0150886637042775, 0.36353122590593628}",
        "hasCurveFrom": true,
        "hasCurveTo": true,
        "point": "{0.99293788170678121, 0.50655358519660665}"
      },
      {
        "_class": "curvePoint",
        "cornerRadius": 0,
        "curveFrom": "{0.27885674002474925, 1}",
        "curveMode": 3,
        "curveTo": "{0.71586538824656087, 1}",
        "hasCurveFrom": true,
        "hasCurveTo": true,
        "point": "{0.42490172641502916, 1}"
      },
      {
        "_class": "curvePoint",
        "cornerRadius": 0,
        "curveFrom": "{0.01267191907177475, 0.76985350809560593}",
        "curveMode": 2,
        "curveTo": "{0.16209583830912794, 0.95181187355435615}",
        "hasCurveFrom": true,
        "hasCurveTo": true,
        "point": "{0.08700844170744379, 0.86044718581341606}"
      },
      {
        "_class": "curvePoint",
        "cornerRadius": 0,
        "curveFrom": "{0.053594550219694143, 0.20470316114109455}",
        "curveMode": 3,
        "curveTo": "{-0.015485854653858476, 0.64109483423284574}",
        "hasCurveFrom": true,
        "hasCurveTo": true,
        "point": "{0.0081666752756734337, 0.49730146491904409}"
      },
      {
        "_class": "curvePoint",
        "cornerRadius": 0,
        "curveFrom": "{0.7154899512635533, 0}",
        "curveMode": 3,
        "curveTo": "{0.28561460571890124, 0}",
        "hasCurveFrom": true,
        "hasCurveTo": true,
        "point": "{0.5724484607373419, 0}"
      },
      {
        "_class": "curvePoint",
        "cornerRadius": 0,
        "curveFrom": "{0.98467826808059633, 0.23361603700848058}",
        "curveMode": 2,
        "curveTo": "{0.83149997901315686, 0.048573631457209457}",
        "hasCurveFrom": true,
        "hasCurveTo": true,
        "point": "{0.90808912354687665, 0.14070932922127941}"
      }
    ]
  },
  "resizingConstraint": 63,
  "resizingType": 0,
  "rotation": 0,
  "shouldBreakMaskChain": false
}